{
	"format_version": "1.12.0",
	"minecraft:geometry": [
		{
			"description": {
				"identifier": "geometry.classic_hammer - Converted",
				"texture_width": 64,
				"texture_height": 64,
				"visible_bounds_width": 2,
				"visible_bounds_height": 4,
				"visible_bounds_offset": [0, 1, 0]
			},
			"bones": [
				{
					"name": "root",
					"pivot": [0, 0, 0],
					"cubes": [
						{
							"origin": [-1, -3, -1],
							"size": [2, 18, 2],
							"uv": {
								"north": {"uv": [2.1, 20.1], "uv_size": [1.8, 17.8]},
								"east": {"uv": [4.1, 20.1], "uv_size": [1.8, 17.8]},
								"south": {"uv": [6.1, 20.1], "uv_size": [1.8, 17.8]},
								"west": {"uv": [8.1, 20.1], "uv_size": [1.8, 17.8]},
								"up": {"uv": [28.1, 14.1], "uv_size": [1.8, 1.8]},
								"down": {"uv": [28.1, 17.9], "uv_size": [1.8, -1.8]}
							}
						},
						{
							"origin": [-1.2, -3.2, -1.2],
							"size": [2.4, 18.4, 2.4],
							"uv": {
								"north": {"uv": [18.1, 0.1], "uv_size": [1.8, 17.8]},
								"east": {"uv": [18.1, 18.1], "uv_size": [1.8, 17.8]},
								"south": {"uv": [0.1, 20.1], "uv_size": [1.8, 17.8]},
								"west": {"uv": [20.1, 0.1], "uv_size": [1.8, 17.8]},
								"up": {"uv": [16.1, 23.1], "uv_size": [1.8, 1.8]},
								"down": {"uv": [28.1, 13.9], "uv_size": [1.8, -1.8]}
							}
						},
						{
							"origin": [-1.4, 22, -1.3],
							"size": [2.8, 3, 3],
							"pivot": [0, 23.5, 0.2],
							"rotation": [-7.5, 0, 0],
							"uv": {
								"north": {"uv": [36.1, 18.1], "uv_size": [2.8, 2.8]},
								"east": {"uv": [36.1, 21.1], "uv_size": [2.8, 2.8]},
								"south": {"uv": [30.1, 36.1], "uv_size": [2.8, 2.8]},
								"west": {"uv": [33.1, 36.1], "uv_size": [2.8, 2.8]},
								"up": {"uv": [36.1, 36.1], "uv_size": [2.8, 2.8]},
								"down": {"uv": [0.1, 40.9], "uv_size": [2.8, -2.8]}
							}
						},
						{
							"origin": [-1.6, 21.8, -1.5],
							"size": [3.2, 3.4, 3.4],
							"pivot": [0, 23.5, 0.2],
							"rotation": [-7.5, 0, 0],
							"uv": {
								"north": {"uv": [3.1, 38.1], "uv_size": [2.8, 2.8]},
								"east": {"uv": [6.1, 38.1], "uv_size": [2.8, 2.8]},
								"south": {"uv": [9.1, 38.1], "uv_size": [2.8, 2.8]},
								"west": {"uv": [12.1, 38.1], "uv_size": [2.8, 2.8]},
								"up": {"uv": [22.1, 38.1], "uv_size": [2.8, 2.8]},
								"down": {"uv": [38.1, 26.9], "uv_size": [2.8, -2.8]}
							}
						},
						{
							"origin": [-3, 17, -2.5],
							"size": [6, 6, 6],
							"pivot": [0, 20.5, 0],
							"rotation": [-45, 0, 0],
							"uv": {
								"north": {"uv": [10.1, 20.1], "uv_size": [5.8, 5.8]},
								"east": {"uv": [20.1, 18.1], "uv_size": [5.8, 5.8]},
								"south": {"uv": [22.1, 0.1], "uv_size": [5.8, 5.8]},
								"west": {"uv": [22.1, 6.1], "uv_size": [5.8, 5.8]},
								"up": {"uv": [22.1, 12.1], "uv_size": [5.8, 5.8]},
								"down": {"uv": [20.1, 29.9], "uv_size": [5.8, -5.8]}
							}
						},
						{
							"origin": [-2, 17.8, 1.9],
							"size": [4, 4, 4],
							"pivot": [0, 19.8, 1.9],
							"rotation": [-7.5, 0, 0],
							"uv": {
								"north": {"uv": [22.1, 30.1], "uv_size": [3.8, 3.8]},
								"east": {"uv": [30.1, 24.1], "uv_size": [3.8, 3.8]},
								"south": {"uv": [26.1, 30.1], "uv_size": [3.8, 3.8]},
								"west": {"uv": [30.1, 28.1], "uv_size": [3.8, 3.8]},
								"up": {"uv": [32.1, 0.1], "uv_size": [3.8, 3.8]},
								"down": {"uv": [32.1, 7.9], "uv_size": [3.8, -3.8]}
							}
						},
						{
							"origin": [-2.2, 17.6, 1.7],
							"size": [4.4, 4.4, 4.4],
							"pivot": [0, 19.8, 1.9],
							"rotation": [-7.5, 0, 0],
							"uv": {
								"north": {"uv": [32.1, 8.1], "uv_size": [3.8, 3.8]},
								"east": {"uv": [10.1, 32.1], "uv_size": [3.8, 3.8]},
								"south": {"uv": [32.1, 12.1], "uv_size": [3.8, 3.8]},
								"west": {"uv": [14.1, 32.1], "uv_size": [3.8, 3.8]},
								"up": {"uv": [32.1, 16.1], "uv_size": [3.8, 3.8]},
								"down": {"uv": [32.1, 23.9], "uv_size": [3.8, -3.8]}
							}
						},
						{
							"origin": [-2, 16.3, -5],
							"size": [4, 6, 4],
							"pivot": [-2, 19.3, -6.5],
							"rotation": [5, 0, 0],
							"uv": {
								"north": {"uv": [10.1, 26.1], "uv_size": [3.8, 5.8]},
								"east": {"uv": [14.1, 26.1], "uv_size": [3.8, 5.8]},
								"south": {"uv": [26.1, 18.1], "uv_size": [3.8, 5.8]},
								"west": {"uv": [26.1, 24.1], "uv_size": [3.8, 5.8]},
								"up": {"uv": [30.1, 32.1], "uv_size": [3.8, 3.8]},
								"down": {"uv": [22.1, 37.9], "uv_size": [3.8, -3.8]}
							}
						},
						{
							"origin": [-4, 14.3, -10],
							"size": [8, 10, 5],
							"pivot": [-2, 19.3, -6.5],
							"rotation": [5, 0, 0],
							"uv": {
								"north": {"uv": [0.1, 0.1], "uv_size": [7.8, 9.8]},
								"east": {"uv": [0.1, 10.1], "uv_size": [4.8, 9.8]},
								"south": {"uv": [8.1, 0.1], "uv_size": [7.8, 9.8]},
								"west": {"uv": [5.1, 10.1], "uv_size": [4.8, 9.8]},
								"up": {"uv": [10.1, 10.1], "uv_size": [7.8, 4.8]},
								"down": {"uv": [10.1, 19.9], "uv_size": [7.8, -4.8]}
							}
						},
						{
							"origin": [-3, 23.3, -11],
							"size": [6, 2, 2],
							"pivot": [-2, 19.3, -6.5],
							"rotation": [5, 0, 0],
							"uv": {
								"north": {"uv": [36.1, 0.1], "uv_size": [5.8, 1.8]},
								"east": {"uv": [25.1, 41.1], "uv_size": [1.8, 1.8]},
								"south": {"uv": [36.1, 2.1], "uv_size": [5.8, 1.8]},
								"west": {"uv": [41.1, 26.1], "uv_size": [1.8, 1.8]},
								"up": {"uv": [36.1, 4.1], "uv_size": [5.8, 1.8]},
								"down": {"uv": [36.1, 7.9], "uv_size": [5.8, -1.8]}
							}
						},
						{
							"origin": [-3, 13.3, -11],
							"size": [6, 2, 2],
							"pivot": [-2, 19.3, -6.5],
							"rotation": [5, 0, 0],
							"uv": {
								"north": {"uv": [36.1, 8.1], "uv_size": [5.8, 1.8]},
								"east": {"uv": [27.1, 41.1], "uv_size": [1.8, 1.8]},
								"south": {"uv": [10.1, 36.1], "uv_size": [5.8, 1.8]},
								"west": {"uv": [41.1, 28.1], "uv_size": [1.8, 1.8]},
								"up": {"uv": [36.1, 10.1], "uv_size": [5.8, 1.8]},
								"down": {"uv": [36.1, 13.9], "uv_size": [5.8, -1.8]}
							}
						},
						{
							"origin": [-5, 13.3, -11],
							"size": [2, 12, 2],
							"pivot": [-2, 19.3, -6.5],
							"rotation": [5, 0, 0],
							"uv": {
								"north": {"uv": [28.1, 0.1], "uv_size": [1.8, 11.8]},
								"east": {"uv": [30.1, 0.1], "uv_size": [1.8, 11.8]},
								"south": {"uv": [30.1, 12.1], "uv_size": [1.8, 11.8]},
								"west": {"uv": [20.1, 30.1], "uv_size": [1.8, 11.8]},
								"up": {"uv": [29.1, 41.1], "uv_size": [1.8, 1.8]},
								"down": {"uv": [41.1, 31.9], "uv_size": [1.8, -1.8]}
							}
						},
						{
							"origin": [3, 13.3, -11],
							"size": [2, 12, 2],
							"pivot": [2, 19.3, -6.5],
							"rotation": [5, 0, 0],
							"uv": {
								"north": {"uv": [29.9, 0.1], "uv_size": [-1.8, 11.8]},
								"east": {"uv": [21.9, 30.1], "uv_size": [-1.8, 11.8]},
								"south": {"uv": [31.9, 12.1], "uv_size": [-1.8, 11.8]},
								"west": {"uv": [31.9, 0.1], "uv_size": [-1.8, 11.8]},
								"up": {"uv": [30.9, 41.1], "uv_size": [-1.8, 1.8]},
								"down": {"uv": [42.9, 31.9], "uv_size": [-1.8, -1.8]}
							}
						},
						{
							"origin": [-5, 13.3, -9],
							"size": [3, 3, 2],
							"pivot": [-2, 19.3, -6.5],
							"rotation": [5, 0, 0],
							"uv": {
								"north": {"uv": [25.1, 38.1], "uv_size": [2.8, 2.8]},
								"east": {"uv": [16.1, 0.1], "uv_size": [1.8, 2.8]},
								"south": {"uv": [38.1, 27.1], "uv_size": [2.8, 2.8]},
								"west": {"uv": [16.1, 3.1], "uv_size": [1.8, 2.8]},
								"up": {"uv": [40.1, 40.1], "uv_size": [2.8, 1.8]},
								"down": {"uv": [0.1, 42.9], "uv_size": [2.8, -1.8]}
							}
						},
						{
							"origin": [-5, 22.3, -9],
							"size": [3, 3, 2],
							"pivot": [-2, 19.3, -6.5],
							"rotation": [5, 0, 0],
							"uv": {
								"north": {"uv": [38.1, 30.1], "uv_size": [2.8, 2.8]},
								"east": {"uv": [16.1, 6.1], "uv_size": [1.8, 2.8]},
								"south": {"uv": [38.1, 33.1], "uv_size": [2.8, 2.8]},
								"west": {"uv": [16.1, 20.1], "uv_size": [1.8, 2.8]},
								"up": {"uv": [3.1, 41.1], "uv_size": [2.8, 1.8]},
								"down": {"uv": [6.1, 42.9], "uv_size": [2.8, -1.8]}
							}
						},
						{
							"origin": [2, 13.3, -9],
							"size": [3, 3, 2],
							"pivot": [2, 19.3, -6.5],
							"rotation": [5, 0, 0],
							"uv": {
								"north": {"uv": [27.9, 38.1], "uv_size": [-2.8, 2.8]},
								"east": {"uv": [17.9, 3.1], "uv_size": [-1.8, 2.8]},
								"south": {"uv": [40.9, 27.1], "uv_size": [-2.8, 2.8]},
								"west": {"uv": [17.9, 0.1], "uv_size": [-1.8, 2.8]},
								"up": {"uv": [42.9, 40.1], "uv_size": [-2.8, 1.8]},
								"down": {"uv": [2.9, 42.9], "uv_size": [-2.8, -1.8]}
							}
						},
						{
							"origin": [2, 22.3, -9],
							"size": [3, 3, 2],
							"pivot": [2, 19.3, -6.5],
							"rotation": [5, 0, 0],
							"uv": {
								"north": {"uv": [40.9, 30.1], "uv_size": [-2.8, 2.8]},
								"east": {"uv": [17.9, 20.1], "uv_size": [-1.8, 2.8]},
								"south": {"uv": [40.9, 33.1], "uv_size": [-2.8, 2.8]},
								"west": {"uv": [17.9, 6.1], "uv_size": [-1.8, 2.8]},
								"up": {"uv": [5.9, 41.1], "uv_size": [-2.8, 1.8]},
								"down": {"uv": [8.9, 42.9], "uv_size": [-2.8, -1.8]}
							}
						},
						{
							"origin": [-1.5, -5, -1.5],
							"size": [3, 2, 3],
							"pivot": [0, -2.5, 0],
							"rotation": [0, 45, 0],
							"uv": {
								"north": {"uv": [9.1, 41.1], "uv_size": [2.8, 1.8]},
								"east": {"uv": [12.1, 41.1], "uv_size": [2.8, 1.8]},
								"south": {"uv": [22.1, 41.1], "uv_size": [2.8, 1.8]},
								"west": {"uv": [41.1, 24.1], "uv_size": [2.8, 1.8]},
								"up": {"uv": [39.1, 14.1], "uv_size": [2.8, 2.8]},
								"down": {"uv": [39.1, 19.9], "uv_size": [2.8, -2.8]}
							}
						},
						{
							"origin": [0, -9, -1.5],
							"size": [0, 4, 3],
							"pivot": [0, -2.5, 0],
							"rotation": [0, 45, 0],
							"uv": {
								"north": {"uv": [0.1, 0.1], "uv_size": [0, 3.8]},
								"east": {"uv": [18.9, 36.1], "uv_size": [-2.8, 3.8]},
								"south": {"uv": [0.1, 0.1], "uv_size": [0, 3.8]},
								"west": {"uv": [16.1, 36.1], "uv_size": [2.8, 3.8]},
								"up": {"uv": [0.1, 0.1], "uv_size": [0, 2.8]},
								"down": {"uv": [0.1, 2.9], "uv_size": [0, -2.8]}
							}
						},
						{
							"origin": [0, -9, -1.5],
							"size": [0, 4, 3],
							"pivot": [0, -2.5, 0],
							"rotation": [0, -45, 0],
							"uv": {
								"north": {"uv": [0.1, 0.1], "uv_size": [0, 3.8]},
								"east": {"uv": [18.9, 36.1], "uv_size": [-2.8, 3.8]},
								"south": {"uv": [0.1, 0.1], "uv_size": [0, 3.8]},
								"west": {"uv": [16.1, 36.1], "uv_size": [2.8, 3.8]},
								"up": {"uv": [0.1, 0.1], "uv_size": [0, 2.8]},
								"down": {"uv": [0.1, 2.9], "uv_size": [0, -2.8]}
							}
						},
						{
							"origin": [-2, -2, -2],
							"size": [4, 2, 4],
							"pivot": [0, -2.5, 0],
							"rotation": [0, 45, 0],
							"uv": {
								"north": {"uv": [39.1, 20.1], "uv_size": [3.8, 1.8]},
								"east": {"uv": [39.1, 22.1], "uv_size": [3.8, 1.8]},
								"south": {"uv": [28.1, 39.1], "uv_size": [3.8, 1.8]},
								"west": {"uv": [32.1, 39.1], "uv_size": [3.8, 1.8]},
								"up": {"uv": [34.1, 24.1], "uv_size": [3.8, 3.8]},
								"down": {"uv": [26.1, 37.9], "uv_size": [3.8, -3.8]}
							}
						},
						{
							"origin": [-2, 15, -2],
							"size": [4, 2, 4],
							"pivot": [0, 16, 0],
							"rotation": [0, 45, 0],
							"uv": {
								"north": {"uv": [36.1, 39.1], "uv_size": [3.8, 1.8]},
								"east": {"uv": [39.1, 36.1], "uv_size": [3.8, 1.8]},
								"south": {"uv": [15.1, 40.1], "uv_size": [3.8, 1.8]},
								"west": {"uv": [40.1, 38.1], "uv_size": [3.8, 1.8]},
								"up": {"uv": [34.1, 28.1], "uv_size": [3.8, 3.8]},
								"down": {"uv": [34.1, 35.9], "uv_size": [3.8, -3.8]}
							}
						}
					]
				}
			]
		}
	]
}